dormyboba/__init__.py
dormyboba/config.py
dormyboba/handlers/__init__.py
dormyboba/handlers/common.py
dormyboba/handlers/defect.py
dormyboba/handlers/invite.py
dormyboba/handlers/mailing.py
dormyboba/handlers/queue.py
dormyboba/handlers/random.py
dormyboba-0.1.0.dist-info/LICENSE
dormyboba-0.1.0.dist-info/METADATA
dormyboba-0.1.0.dist-info/WHEEL
dormyboba-0.1.0.dist-info/entry_points.txt
dormyboba-0.1.0.dist-info/RECORD
